<?xml version="1.0" encoding="UTF-8"?>
<!DOCTYPE mapper PUBLIC "-//mybatis.org//DTD Mapper 3.0//EN" "http://mybatis.org/dtd/mybatis-3-mapper.dtd">
<mapper namespace="com.qimeng.bs.market.activity.dao.DmMerchantActivityMapper">
  <resultMap id="BaseResultMap" type="com.qimeng.bs.market.activity.bean.DmMerchantActivity">
    <!--
      WARNING - @mbggenerated
      This element is automatically generated by MyBatis Generator, do not modify.
      This element was generated on Thu Dec 05 10:40:08 CST 2013.
    -->
    <id column="ACT_ID" jdbcType="INTEGER" property="actId" />
    <result column="GOODS_INST_ID" jdbcType="INTEGER" property="goodsInstId" />
    <result column="MERCHANT_ID" jdbcType="INTEGER" property="merchantId" />
    <result column="ACT_NAME" jdbcType="VARCHAR" property="actName" />
    <result column="SEND_METHOD" jdbcType="VARCHAR" property="sendMethod" />
    <result column="SMS_CONTENT" jdbcType="VARCHAR" property="smsContent" />
    <result column="BEGIN_TIME" jdbcType="TIMESTAMP" property="beginTime" />
    <result column="END_TIME" jdbcType="TIMESTAMP" property="endTime" />
    <result column="PRODUCE_TIME" jdbcType="TIMESTAMP" property="produceTime" />
    <result column="RULE_TIME" jdbcType="VARCHAR" property="ruleTime" />
    <result column="CREATE_TIME" jdbcType="TIMESTAMP" property="createTime" />
    <result column="STATE" jdbcType="VARCHAR" property="state" />
    <result column="STATE_TIME" jdbcType="TIMESTAMP" property="stateTime" />
  </resultMap>
  <sql id="Base_Column_List">
    <!--
      WARNING - @mbggenerated
      This element is automatically generated by MyBatis Generator, do not modify.
      This element was generated on Thu Dec 05 10:40:08 CST 2013.
    -->
    ACT_ID, GOODS_INST_ID, MERCHANT_ID, ACT_NAME, SEND_METHOD, SMS_CONTENT, BEGIN_TIME, 
    END_TIME, PRODUCE_TIME, RULE_TIME, CREATE_TIME, STATE, STATE_TIME
  </sql>
  <select id="selectByPrimaryKey" parameterType="java.lang.Integer" resultMap="BaseResultMap">
    <!--
      WARNING - @mbggenerated
      This element is automatically generated by MyBatis Generator, do not modify.
      This element was generated on Thu Dec 05 10:40:08 CST 2013.
    -->
    select 
    <include refid="Base_Column_List" />
    from dm_merchant_activity
    where ACT_ID = #{actId,jdbcType=INTEGER}
  </select>

    <resultMap id="MyActivityMap" type="com.qimeng.bs.market.activity.bean.DmMerchantActivity">
        <id column="ACT_ID" jdbcType="INTEGER" property="actId" />
        <result column="GOODS_INST_ID" jdbcType="INTEGER" property="goodsInstId" />
        <result column="MERCHANT_ID" jdbcType="INTEGER" property="merchantId" />
        <result column="ACT_NAME" jdbcType="VARCHAR" property="actName" />
        <result column="SEND_METHOD" jdbcType="VARCHAR" property="sendMethod" />
        <result column="SMS_CONTENT" jdbcType="VARCHAR" property="smsContent" />
        <result column="BEGIN_TIME" jdbcType="TIMESTAMP" property="beginTime" />
        <result column="END_TIME" jdbcType="TIMESTAMP" property="endTime" />
        <result column="PRODUCE_TIME" jdbcType="TIMESTAMP" property="produceTime" />
        <result column="RULE_TIME" jdbcType="VARCHAR" property="ruleTime" />
        <result column="CREATE_TIME" jdbcType="TIMESTAMP" property="createTime" />
        <result column="STATE" jdbcType="VARCHAR" property="state" />
        <result column="STATE_TIME" jdbcType="TIMESTAMP" property="stateTime" />
        <result column="GOODS_NAME" jdbcType="VARCHAR" property="goodsName" />
        <!--<association property="goodsName" resultMap="GoodsInstMap"/>-->
    </resultMap>
    <!--<resultMap id="GoodsInstMap" type="com.qimengeda.market.goods.bean.DmGoodsInst">
        <id column="INST_ID" jdbcType="INTEGER" property="instId" />
        <result column="GOODS_NAME" jdbcType="VARCHAR" property="goodsName" />
    </resultMap>-->
    <select id="selectMerchantActivityList"
            resultMap="MyActivityMap" parameterType="Page">
        select
            a.*,
            b.GOODS_NAME
        FROM
          dm_merchant_activity a LEFT JOIN dm_goods_inst b ON a.GOODS_INST_ID = b.INST_ID
        <where>
            <trim prefix="(" prefixOverrides="and" suffix=")">
                <if test="params.merchantId!=null">
                    and a.merchant_id = #{merchantId}
                </if>
                <if test="params.actName!=null">
                    and a.act_name like #{actName}
                </if>
                <if test="params.state!=null">
                    and a.state = #{state}
                </if>
            </trim>
        </where>
        order by a.state_time desc
    </select>
    <delete id="deleteByPrimaryKey" parameterType="java.lang.Integer">
    <!--
      WARNING - @mbggenerated
      This element is automatically generated by MyBatis Generator, do not modify.
      This element was generated on Thu Dec 05 10:40:08 CST 2013.
    -->
    delete from dm_merchant_activity
    where ACT_ID = #{actId,jdbcType=INTEGER}
  </delete>
  <insert id="insert" parameterType="com.qimeng.bs.market.activity.bean.DmMerchantActivity">
    <!--
      WARNING - @mbggenerated
      This element is automatically generated by MyBatis Generator, do not modify.
      This element was generated on Thu Dec 05 10:40:08 CST 2013.
    -->
    insert into dm_merchant_activity (ACT_ID, GOODS_INST_ID, MERCHANT_ID, 
      ACT_NAME, SEND_METHOD, SMS_CONTENT, 
      BEGIN_TIME, END_TIME, PRODUCE_TIME, 
      RULE_TIME, CREATE_TIME, STATE, 
      STATE_TIME)
    values (#{actId,jdbcType=INTEGER}, #{goodsInstId,jdbcType=INTEGER}, #{merchantId,jdbcType=INTEGER}, 
      #{actName,jdbcType=VARCHAR}, #{sendMethod,jdbcType=VARCHAR}, #{smsContent,jdbcType=VARCHAR}, 
      #{beginTime,jdbcType=TIMESTAMP}, #{endTime,jdbcType=TIMESTAMP}, #{produceTime,jdbcType=TIMESTAMP}, 
      #{ruleTime,jdbcType=VARCHAR}, #{createTime,jdbcType=TIMESTAMP}, #{state,jdbcType=VARCHAR}, 
      #{stateTime,jdbcType=TIMESTAMP})
  </insert>
  <insert id="insertSelective" parameterType="com.qimeng.bs.market.activity.bean.DmMerchantActivity">
    <!--
      WARNING - @mbggenerated
      This element is automatically generated by MyBatis Generator, do not modify.
      This element was generated on Thu Dec 05 10:40:08 CST 2013.
    -->
    insert into dm_merchant_activity
    <trim prefix="(" suffix=")" suffixOverrides=",">
      <if test="actId != null">
        ACT_ID,
      </if>
      <if test="goodsInstId != null">
        GOODS_INST_ID,
      </if>
      <if test="merchantId != null">
        MERCHANT_ID,
      </if>
      <if test="actName != null">
        ACT_NAME,
      </if>
      <if test="sendMethod != null">
        SEND_METHOD,
      </if>
      <if test="smsContent != null">
        SMS_CONTENT,
      </if>
      <if test="beginTime != null">
        BEGIN_TIME,
      </if>
      <if test="endTime != null">
        END_TIME,
      </if>
      <if test="produceTime != null">
        PRODUCE_TIME,
      </if>
      <if test="ruleTime != null">
        RULE_TIME,
      </if>
      <if test="createTime != null">
        CREATE_TIME,
      </if>
      <if test="state != null">
        STATE,
      </if>
      <if test="stateTime != null">
        STATE_TIME,
      </if>
    </trim>
    <trim prefix="values (" suffix=")" suffixOverrides=",">
      <if test="actId != null">
        #{actId,jdbcType=INTEGER},
      </if>
      <if test="goodsInstId != null">
        #{goodsInstId,jdbcType=INTEGER},
      </if>
      <if test="merchantId != null">
        #{merchantId,jdbcType=INTEGER},
      </if>
      <if test="actName != null">
        #{actName,jdbcType=VARCHAR},
      </if>
      <if test="sendMethod != null">
        #{sendMethod,jdbcType=VARCHAR},
      </if>
      <if test="smsContent != null">
        #{smsContent,jdbcType=VARCHAR},
      </if>
      <if test="beginTime != null">
        #{beginTime,jdbcType=TIMESTAMP},
      </if>
      <if test="endTime != null">
        #{endTime,jdbcType=TIMESTAMP},
      </if>
      <if test="produceTime != null">
        #{produceTime,jdbcType=TIMESTAMP},
      </if>
      <if test="ruleTime != null">
        #{ruleTime,jdbcType=VARCHAR},
      </if>
      <if test="createTime != null">
        #{createTime,jdbcType=TIMESTAMP},
      </if>
      <if test="state != null">
        #{state,jdbcType=VARCHAR},
      </if>
      <if test="stateTime != null">
        #{stateTime,jdbcType=TIMESTAMP},
      </if>
    </trim>
  </insert>
  <update id="updateByPrimaryKeySelective" parameterType="com.qimeng.bs.market.activity.bean.DmMerchantActivity">
    <!--
      WARNING - @mbggenerated
      This element is automatically generated by MyBatis Generator, do not modify.
      This element was generated on Thu Dec 05 10:40:08 CST 2013.
    -->
    update dm_merchant_activity
    <set>
      <if test="goodsInstId != null">
        GOODS_INST_ID = #{goodsInstId,jdbcType=INTEGER},
      </if>
      <if test="merchantId != null">
        MERCHANT_ID = #{merchantId,jdbcType=INTEGER},
      </if>
      <if test="actName != null">
        ACT_NAME = #{actName,jdbcType=VARCHAR},
      </if>
      <if test="sendMethod != null">
        SEND_METHOD = #{sendMethod,jdbcType=VARCHAR},
      </if>
      <if test="smsContent != null">
        SMS_CONTENT = #{smsContent,jdbcType=VARCHAR},
      </if>
      <if test="beginTime != null">
        BEGIN_TIME = #{beginTime,jdbcType=TIMESTAMP},
      </if>
      <if test="endTime != null">
        END_TIME = #{endTime,jdbcType=TIMESTAMP},
      </if>
      <if test="produceTime != null">
        PRODUCE_TIME = #{produceTime,jdbcType=TIMESTAMP},
      </if>
      <if test="ruleTime != null">
        RULE_TIME = #{ruleTime,jdbcType=VARCHAR},
      </if>
      <if test="createTime != null">
        CREATE_TIME = #{createTime,jdbcType=TIMESTAMP},
      </if>
      <if test="state != null">
        STATE = #{state,jdbcType=VARCHAR},
      </if>
      <if test="stateTime != null">
        STATE_TIME = #{stateTime,jdbcType=TIMESTAMP},
      </if>
    </set>
    where ACT_ID = #{actId,jdbcType=INTEGER}
  </update>
  <update id="updateByPrimaryKey" parameterType="com.qimeng.bs.market.activity.bean.DmMerchantActivity">
    <!--
      WARNING - @mbggenerated
      This element is automatically generated by MyBatis Generator, do not modify.
      This element was generated on Thu Dec 05 10:40:08 CST 2013.
    -->
    update dm_merchant_activity
    set GOODS_INST_ID = #{goodsInstId,jdbcType=INTEGER},
      MERCHANT_ID = #{merchantId,jdbcType=INTEGER},
      ACT_NAME = #{actName,jdbcType=VARCHAR},
      SEND_METHOD = #{sendMethod,jdbcType=VARCHAR},
      SMS_CONTENT = #{smsContent,jdbcType=VARCHAR},
      BEGIN_TIME = #{beginTime,jdbcType=TIMESTAMP},
      END_TIME = #{endTime,jdbcType=TIMESTAMP},
      PRODUCE_TIME = #{produceTime,jdbcType=TIMESTAMP},
      RULE_TIME = #{ruleTime,jdbcType=VARCHAR},
      CREATE_TIME = #{createTime,jdbcType=TIMESTAMP},
      STATE = #{state,jdbcType=VARCHAR},
      STATE_TIME = #{stateTime,jdbcType=TIMESTAMP}
    where ACT_ID = #{actId,jdbcType=INTEGER}
  </update>
</mapper>